mb_scripts/__init__.py
mb_scripts/cnn_image_architecture.py
mb_scripts/decomposition.py
mb_scripts/dnn_scripts.py
mb_scripts/feature_selection.py
mb_scripts/metrics.py
mb_scripts/plotting.py
mb_scripts/preprocessing.py
mb_scripts/useful_scripts.py
mb_scripts-0.1.1.dist-info/LICENSE.txt
mb_scripts-0.1.1.dist-info/METADATA
mb_scripts-0.1.1.dist-info/WHEEL
mb_scripts-0.1.1.dist-info/top_level.txt
mb_scripts-0.1.1.dist-info/RECORD
