Metadata-Version: 2.1
Name: mb-scripts
Version: 0.1.1
Summary: Machine Learning scripts that will quicken the modelling and data analysis process
Author: Sathya Krishnan Suresh
Author-email: <satyakrishnan.s@pec.edu>
Keywords: python,mb_scripts,machine learning,data science,data analysis,deep learning
Classifier: Development Status :: 1 - Planning
Classifier: Intended Audience :: Developers
Classifier: Programming Language :: Python :: 3
Classifier: Operating System :: Unix
Classifier: Operating System :: MacOS :: MacOS X
Classifier: Operating System :: Microsoft :: Windows
License-File: LICENSE.txt
Requires-Dist: scikit-learn
Requires-Dist: pandas
Requires-Dist: numpy
Requires-Dist: matplotlib
Requires-Dist: seaborn
Requires-Dist: tensorflow
